omnipy_examples/__init__.py
omnipy_examples/bed.py
omnipy_examples/chatgpt.py
omnipy_examples/chatgpt_words.py
omnipy_examples/dagsim.py
omnipy_examples/deployment.py
omnipy_examples/edam.py
omnipy_examples/encode.py
omnipy_examples/gff.py
omnipy_examples/isa_v1_0_1_models/__init__.py
omnipy_examples/isa_v1_0_1_models/assay_schema.py
omnipy_examples/isa_v1_0_1_models/comment_schema.py
omnipy_examples/isa_v1_0_1_models/data_schema.py
omnipy_examples/isa_v1_0_1_models/factor_schema.py
omnipy_examples/isa_v1_0_1_models/factor_value_schema.py
omnipy_examples/isa_v1_0_1_models/investigation_schema.py
omnipy_examples/isa_v1_0_1_models/material_attribute_schema.py
omnipy_examples/isa_v1_0_1_models/material_attribute_value_schema.py
omnipy_examples/isa_v1_0_1_models/material_schema.py
omnipy_examples/isa_v1_0_1_models/ontology_annotation_schema.py
omnipy_examples/isa_v1_0_1_models/ontology_source_reference_schema.py
omnipy_examples/isa_v1_0_1_models/organization_schema.py
omnipy_examples/isa_v1_0_1_models/person_schema.py
omnipy_examples/isa_v1_0_1_models/process_parameter_value_schema.py
omnipy_examples/isa_v1_0_1_models/process_schema.py
omnipy_examples/isa_v1_0_1_models/protocol_parameter_schema.py
omnipy_examples/isa_v1_0_1_models/protocol_schema.py
omnipy_examples/isa_v1_0_1_models/publication_schema.py
omnipy_examples/isa_v1_0_1_models/sample_schema.py
omnipy_examples/isa_v1_0_1_models/source_schema.py
omnipy_examples/isa_v1_0_1_models/study_group.py
omnipy_examples/isa_v1_0_1_models/study_schema.py
omnipy_examples/isa_v1_0_1_models.old/__init__.py
omnipy_examples/isa_v1_0_1_models.old/assay_schema.py
omnipy_examples/isa_v1_0_1_models.old/comment_schema.py
omnipy_examples/isa_v1_0_1_models.old/data_schema.py
omnipy_examples/isa_v1_0_1_models.old/factor_schema.py
omnipy_examples/isa_v1_0_1_models.old/factor_value_schema.py
omnipy_examples/isa_v1_0_1_models.old/investigation_schema.py
omnipy_examples/isa_v1_0_1_models.old/material_attribute_schema.py
omnipy_examples-0.8.0.dist-info/LICENSE
omnipy_examples-0.8.0.dist-info/METADATA
omnipy_examples-0.8.0.dist-info/WHEEL
omnipy_examples-0.8.0.dist-info/entry_points.txt
omnipy_examples-0.8.0.dist-info/RECORD
