Metadata-Version: 2.3
Name: omnipy-examples
Version: 0.8.0
Summary: 
Author: Sveinung Gundersen
Author-email: sveinugu@gmail.com
Requires-Python: >=3.10,<3.13
Classifier: Programming Language :: Python :: 3
Classifier: Programming Language :: Python :: 3.10
Classifier: Programming Language :: Python :: 3.11
Classifier: Programming Language :: Python :: 3.12
Requires-Dist: boto3 (>=1.35.23,<2.0.0)
Requires-Dist: omnipy (==0.20.1)
Requires-Dist: omnipy-example-data (>=0.1.0,<0.2.0)
Requires-Dist: prefect (>2.20)
Requires-Dist: reader (>=3.4,<4.0)
